MANIFEST.in
Makefile
README.md
requirements.txt
setup.py
fcc_complaints/VERSION
fcc_complaints/caller_id_report.py
fcc_complaints/default.config
fcc_complaints.egg-info/PKG-INFO
fcc_complaints.egg-info/SOURCES.txt
fcc_complaints.egg-info/dependency_links.txt
fcc_complaints.egg-info/requires.txt
fcc_complaints.egg-info/top_level.txt