Metadata-Version: 1.1
Name: fcc-complaints
Version: 0.1.2
Summary: FCC Complaint Data API Wrapper
Home-page: https://github.com/gdoermann/fcc_complaints
Author: Greg Doermann
Author-email: gdoermann@cronosa.com
License: UNKNOWN
Platform: UNKNOWN
Classifier: Development Status :: 4 - Beta
Classifier: Environment :: Web Environment
Classifier: Intended Audience :: Developers
Classifier: License :: OSI Approved :: MIT License
Classifier: Operating System :: OS Independent
Classifier: Programming Language :: Python
Classifier: Programming Language :: Python :: 3
Classifier: Programming Language :: Python :: 3.6
Classifier: Topic :: Software Development :: Libraries :: Python Modules
